firerest76/__init__.py
firerest76/defaults.py
firerest76/exceptions.py
firerest76/mapping.py
firerest76/utils.py
firerest76/version.py
firerest76/fmc/__init__.py
firerest76/fmc/assignment/__init__.py
firerest76/fmc/assignment/policyassignment/__init__.py
firerest76/fmc/audit/__init__.py
firerest76/fmc/audit/auditrecord/__init__.py
firerest76/fmc/chassis/__init__.py
firerest76/fmc/chassis/interface/__init__.py
firerest76/fmc/chassis/networkmodule/__init__.py
firerest76/fmc/chassis/operational/__init__.py
firerest76/fmc/deployment/__init__.py
firerest76/fmc/deployment/deployabledevice/__init__.py
firerest76/fmc/deployment/deployabledevice/deployment/__init__.py
firerest76/fmc/deployment/deployabledevice/pendingchanges/__init__.py
firerest76/fmc/deployment/deploymentrequest/__init__.py
firerest76/fmc/deployment/jobhistory/__init__.py
firerest76/fmc/deployment/rollbackrequest/__init__.py
firerest76/fmc/device/__init__.py
firerest76/fmc/device/devicerecord/__init__.py
firerest76/fmc/device/devicerecord/bridgegroupinterface/__init__.py
firerest76/fmc/device/devicerecord/etherchannelinterface/__init__.py
firerest76/fmc/device/devicerecord/fpinterfacestatistics/__init__.py
firerest76/fmc/device/devicerecord/fplogicalinterface/__init__.py
firerest76/fmc/device/devicerecord/fpphysicalinterface/__init__.py
firerest76/fmc/device/devicerecord/inlineset/__init__.py
firerest76/fmc/device/devicerecord/interfaceevent/__init__.py
firerest76/fmc/device/devicerecord/operational/__init__.py
firerest76/fmc/device/devicerecord/operational/command/__init__.py
firerest76/fmc/device/devicerecord/operational/metric/__init__.py
firerest76/fmc/device/devicerecord/physicalinterface/__init__.py
firerest76/fmc/device/devicerecord/redundantinterface/__init__.py
firerest76/fmc/device/devicerecord/routing/__init__.py
firerest76/fmc/device/devicerecord/routing/bgp/__init__.py
firerest76/fmc/device/devicerecord/routing/bgpgeneralsettings/__init__.py
firerest76-1.2.6.dist-info/licenses/LICENSE
firerest76-1.2.6.dist-info/METADATA
firerest76-1.2.6.dist-info/WHEEL
firerest76-1.2.6.dist-info/top_level.txt
firerest76-1.2.6.dist-info/RECORD
