Metadata-Version: 2.4
Name: firerest76
Version: 1.2.6
Summary: Python API client for Cisco Firepower Management Center (FMC)
Author: Oliver Kaiser
Author-email: Oliver Kaiser <oliver.kaiser@outlook.com>, Rafal Chrabaszcz <rchrabas@cisco.com>, Mushah <mushah@cisco.com>
Maintainer: Rafal Chrabaszcz, Munib Shah
Maintainer-email: rchrabas@cisco.com, mushah@cisco.com
License: GPL-3.0-only
Classifier: Development Status :: 3 - Alpha
Classifier: Intended Audience :: Developers
Classifier: License :: OSI Approved :: GNU General Public License v3 or later (GPLv3+)
Classifier: Programming Language :: Python :: 3
Classifier: Operating System :: OS Independent
Requires-Python: >=3.9
License-File: LICENSE
Requires-Dist: requests>=2.23.0
Requires-Dist: packaging>=20.3
Dynamic: author
Dynamic: license-file
Dynamic: maintainer
Dynamic: maintainer-email
Dynamic: requires-python
